mongoset/__init__.py
mongoset/database.py
mongoset/expression.py
mongoset/model/__init__.py
mongoset/model/base_operations.py
mongoset/model/document_model_objects.py
mongoset/model/immutable_arguments.py
mongoset/model/model_table.py
mongoset-0.3.3.dist-info/LICENSE
mongoset-0.3.3.dist-info/WHEEL
mongoset-0.3.3.dist-info/METADATA
mongoset-0.3.3.dist-info/RECORD
